expdf/__init__.py
expdf/cli.py
expdf/extractor.py
expdf/parser.py
expdf/pdfnode.py
expdf/processors.py
expdf/templates.py
expdf/utils.py
expdf/visualize.py
expdf/xmp.py
expdf-0.3.0.dist-info/LICENCE
expdf-0.3.0.dist-info/METADATA
expdf-0.3.0.dist-info/WHEEL
expdf-0.3.0.dist-info/entry_points.txt
expdf-0.3.0.dist-info/top_level.txt
expdf-0.3.0.dist-info/RECORD
