Metadata-Version: 2.1
Name: expdf
Version: 0.3.0
Summary: PDF Download and Analysis Tool
Home-page: https://github.com/bupt-ipcr/expdf
Author: ('Jiawei Wu',)
Author-email: 13260322877@163.com
License: MIT
Platform: UNKNOWN
Classifier: License :: OSI Approved :: MIT License
Classifier: Programming Language :: Python
Classifier: Programming Language :: Python :: 3
Classifier: Programming Language :: Python :: 3.6
Classifier: Programming Language :: Python :: 3.7
Requires-Python: >=3.6.0
Requires-Dist: requests
Requires-Dist: pdfminer2
Requires-Dist: tqdm
Requires-Dist: networkx
Requires-Dist: plotly
Provides-Extra: test
Requires-Dist: pytest ; extra == 'test'
